Metadata-Version: 2.1
Name: mlagents-envs
Version: 1.1.0
Summary: Unity Machine Learning Agents Interface
Home-page: https://github.com/Unity-Technologies/ml-agents
Author: Unity Technologies
Author-email: ML-Agents@unity3d.com
Classifier: Intended Audience :: Developers
Classifier: Topic :: Scientific/Engineering :: Artificial Intelligence
Classifier: License :: OSI Approved :: Apache Software License
Classifier: Programming Language :: Python :: 3.10
Requires-Python: >=3.10.1,<=3.10.12
